gregorian_months/__init__.py
gregorian_months/gregorian_months.py
gregorian_months-1.1.0.dist-info/METADATA
gregorian_months-1.1.0.dist-info/WHEEL
gregorian_months-1.1.0.dist-info/top_level.txt
gregorian_months-1.1.0.dist-info/RECORD
