Metadata-Version: 2.1
Name: gregorian-months
Version: 1.1.0
Summary: Conduct with the Gregorian calendar months
Home-page: https://github.com/iftahro/gregorian-months
Author: Iftah Roichman
License: UNKNOWN
Platform: UNKNOWN
